Metadata-Version: 2.1
Name: xzutils
Version: 0.0.5
Summary: Sean Python package
Author: Sean
Author-email: <xz.sean.g@gmail.com>
